esprima/__init__.py
esprima/__main__.py
esprima/character.py
esprima/comment_handler.py
esprima/compat.py
esprima/error_handler.py
esprima/esprima.py
esprima/jsx_nodes.py
esprima/jsx_parser.py
esprima/jsx_syntax.py
esprima/messages.py
esprima/nodes.py
esprima/objects.py
esprima/parser.py
esprima/scanner.py
esprima/syntax.py
esprima/token.py
esprima/tokenizer.py
esprima/utils.py
esprima/visitor.py
esprima/xhtml_entities.py
examples/visitor.py
esprima_fork-4.0.4.dist-info/METADATA
esprima_fork-4.0.4.dist-info/WHEEL
esprima_fork-4.0.4.dist-info/licenses/LICENSE
esprima_fork-4.0.4.dist-info/licenses/LICENSE.BSD
esprima_fork-4.0.4.dist-info/RECORD
