Metadata-Version: 2.1
Name: esprima-fork
Version: 4.0.4
Summary: ECMAScript parsing infrastructure for multipurpose analysis in Python
Project-URL: Homepage, https://github.com/Kronuz/esprima-python
Author-email: "German M. Bravo (Kronuz)" <german.mb@gmail.com>
License-File: LICENSE
License-File: LICENSE.BSD
Keywords: ast,ecmascript,esprima,javascript,parser
Classifier: Development Status :: 5 - Production/Stable
Classifier: Intended Audience :: Developers
Classifier: License :: OSI Approved :: BSD License
Classifier: Operating System :: OS Independent
Classifier: Programming Language :: Python
Classifier: Programming Language :: Python :: 3.6
Classifier: Topic :: Software Development :: Code Generators
Classifier: Topic :: Software Development :: Compilers
Classifier: Topic :: Software Development :: Libraries :: Python Modules
Classifier: Topic :: Text Processing :: General
Requires-Python: >=3.6
